vizno/__init__.py
vizno/api.py
vizno/cli.py
vizno/magic.py
vizno/py.typed
vizno/report.py
vizno/server.py
vizno/utils.py
vizno/js/elements.js
vizno/js/hooks.js
vizno/js/renderers.js
vizno/js/vizno-core.js
vizno/renderers/__init__.py
vizno/renderers/altair.py
vizno/renderers/bokeh.py
vizno/renderers/code.py
vizno/renderers/latex.py
vizno/renderers/mathjax.py
vizno/renderers/matplotlib.py
vizno/renderers/plotly.py
vizno/renderers/pygal.py
vizno/renderers/svg.py
vizno/renderers/table.py
vizno/statics/__init__.py
vizno/statics/index.html
vizno/statics/vizno-core.min.js
vizno/statics/vizno.css
vizno/statics/vz-ico.png
vizno-0.1.1.dist-info/LICENSE
vizno-0.1.1.dist-info/METADATA
vizno-0.1.1.dist-info/WHEEL
vizno-0.1.1.dist-info/entry_points.txt
vizno-0.1.1.dist-info/top_level.txt
vizno-0.1.1.dist-info/RECORD
