Metadata-Version: 2.1
Name: vizno
Version: 0.1.1
Summary: Visual layout for python.
Home-page: UNKNOWN
License: MIT
Project-URL: Documentation, https://victorbenichoux.github.io/vizno/
Project-URL: Code, https://github.com/victorbenichoux/vizno
Project-URL: Issue tracker, https://github.com/victorbenichoux/vizno/issues
Platform: UNKNOWN
Classifier: Programming Language :: Python :: 3
Classifier: Programming Language :: Python :: 3.7
Requires-Dist: typer
Requires-Dist: pydantic
Requires-Dist: fastapi
Provides-Extra: dev
Requires-Dist: requests ; extra == 'dev'
Requires-Dist: aiofiles ; extra == 'dev'
Requires-Dist: uvicorn ; extra == 'dev'
Requires-Dist: websockets ; extra == 'dev'
